{
  "id": "33ae3564-8111-457a-ab66-f083d1e20e4b",
  "name": "roytang",
  "url": "https://twitter.com/roytang",
  "text": "When the movie comes out, I want Forrest Whitaker to play this diner guy. Also, I tried out the demo for a bit, feels pretty much like the console version, I'm not sure what I expected{{% collections-embed albums ff15 DXDB5IDVAAcd33t %}}",
  "date": "2018-02-27 22:04:59 +0800",
  "photo": null,
  "source_url": "https://twitter.com/roytang/statuses/968487126022086657/",
  "source": "twitter",
  "spam": false
}