{
  "id": "c0ee3c81-a002-41b6-b9de-4e5f52be5cb6",
  "name": "Kimo Salen",
  "url": "https://www.facebook.com/kimosalen",
  "text": "via youtube, yes.",
  "date": "2013-12-30 00:00:09",
  "photo": null,
  "source_url": "https://www.facebook.com/stephen.roy.tang/posts/10152693511073912#10152693850613912",
  "source_obj": {
    "id": "10152693850613912",
    "poster": "Kimo Salen",
    "poster_url": "/kimosalen?refid=52&_ft_=mf_story_key.10152693511073912%3Atop_level_post_id.10152693511073912%3Atl_objid.10152693511073912%3Acontent_owner_id_new.632418911%3Athrowback_story_fbid.10152693511073912%3Astory_location.4%3Athid.632418911&__tn__=R",
    "text": "via youtube, yes.",
    "attachments": [],
    "date": "Dec 30, 2013"
  }
}