{
  "id": "4123d626-f9a4-4bb9-a349-1e09e30d789b",
  "name": "Areej Pimentel Munar",
  "url": "https://www.facebook.com/areej.munar",
  "text": "Milk",
  "date": "2016-02-29 00:00:01",
  "photo": null,
  "source_url": "https://www.facebook.com/stephen.roy.tang/posts/10154404052703912#10154404055683912",
  "source_obj": {
    "id": "10154404055683912",
    "poster": "Areej Pimentel Munar",
    "poster_url": "/areej.munar?refid=52&_ft_=mf_story_key.10154404052703912%3Atop_level_post_id.10154404052703912%3Atl_objid.10154404052703912%3Acontent_owner_id_new.632418911%3Athrowback_story_fbid.10154404052703912%3Astory_location.4%3Athid.632418911&__tn__=R",
    "text": "Milk",
    "attachments": [],
    "date": "Feb 29, 2016"
  }
}