{
  "id": "cc2ef575-7d95-48fd-a0c2-b70f45ca79fe",
  "name": "Ritchie Tiongson",
  "url": "https://www.facebook.com/ritchie.tiongson",
  "text": "I'd really like more info on the senators. especially the new candidates",
  "date": "2016-04-11 16:00:10 +0000",
  "photo": "",
  "source_url": "https://www.facebook.com/stephen.roy.tang/posts/10154526338333912#10154526348298912#10154527335423912",
  "source": "facebook",
  "spam": false,
  "reply_to": "https://www.facebook.com/stephen.roy.tang/posts/10154526338333912#10154526348298912"
}