{
  "id": "e3e691c9-9f23-4baa-af69-92f5161c4ebe",
  "name": "Shalom Brian Mercader",
  "url": "https://www.facebook.com/shalombrian.mercader",
  "text": "Yeah, blame it on entropy.",
  "date": "2016-04-07 00:03:20",
  "photo": null,
  "source_url": "https://www.facebook.com/stephen.roy.tang/posts/10154516310758912#10154516393943912",
  "source_obj": {
    "id": "10154516393943912",
    "poster": "Shalom Brian Mercader",
    "poster_url": "/shalombrian.mercader?__tn__=R",
    "text": "Yeah, blame it on entropy.",
    "attachments": [],
    "date": "Apr 7, 2016",
    "replyto": "10154516393303912"
  },
  "reply_to": "https://www.facebook.com/stephen.roy.tang/posts/10154516310758912#10154516393303912"
}