{
  "id": "f6e2e2b0-a277-4ac7-9273-8acc766d5127",
  "name": "limbertqc",
  "url": "https://twitter.com/limbertqc",
  "text": "In a #ParliamentarySystem clowns like Panty wont even get a committee chairmanship. In a #PresidentialSystem where the disbursement of emergency, unprogrammed, intelligence funds is under the Pres, Congress members are mere pawns. \n\n{{% quoted url=\"https://twitter.com/roytang/status/968685366789091328\" label=\"roytang's tweet\" %}}\n\n[@limbertqc](https://twitter.com/limbertqc/) I like the idea of parliament in theory, but wont this give more power to clowns like Alvarez?\n\n{{% /quoted %}}",
  "date": "2018-02-28 03:23:42",
  "photo": "https://pbs.twimg.com/profile_images/1080018916003303424/h-mfcbhQ_normal.jpg",
  "source_url": "https://twitter.com/limbertqc/status/968688129203843073/",
  "source": "twitter"
}