{
  "id": "3c8eb4a4-4bae-454e-baf5-e67fa8dacacd",
  "name": "Roy Tang",
  "url": "https://facebook.com/stephen.roy.tang",
  "text": "Thanks  Jocris Angeles Bitoon ! I PM'ed you. Hope you and your family are doing ok",
  "date": "2020-03-30 21:27:06",
  "photo": "",
  "source_url": "https://www.facebook.com/stephen.roy.tang/posts/10158315867473912#10158315871838912#10158315896023912",
  "source": "facebook",
  "spam": false,
  "reply_to": "https://www.facebook.com/stephen.roy.tang/posts/10158315867473912#10158315871838912"
}