{
  "id": "2ddb777a-ca1a-4225-85d1-942e7b84c1c7",
  "name": "Jvee Veneracion",
  "url": "https://www.facebook.com/jvee.veneracion",
  "text": "Because he also appeals to the lowest common denominator. That's where most of the trolls are.",
  "date": "2016-05-09 03:24:11 +0800",
  "photo": null,
  "source_url": "https://www.facebook.com/stephen.roy.tang/posts/10154586646203912#10154587263413912",
  "source": "facebook",
  "spam": false,
  "reply_to": "https://www.facebook.com/stephen.roy.tang/posts/10154586646203912#10154587249063912"
}