{
  "id": "33c9c564-0211-402b-9bf0-d66492279172",
  "name": "Daniel Rey Cimafranca",
  "url": "https://www.facebook.com/danielrey.cimafranca",
  "text": "Any system we come up with will have its flaws.  To err is human after all and we are living in the kingdom of man, not in the perfect kingdom of God.  Ganun talaga sa separation of church and state, it becomes a legal issue.  Let&#x27;s not forget why such separation is in our Constitution.  My personal take on it, dont get mad get even kasi nandyan na yan eh.  What can we do legally para bwisitin ang mga Marcos \u00fc",
  "date": "2016-11-19 00:11:56",
  "photo": null,
  "source_url": "https://www.facebook.com/stephen.roy.tang/posts/10155102720598912#10155103547623912",
  "source_obj": {
    "id": "10155103547623912",
    "poster": "Daniel Rey Cimafranca",
    "poster_url": "/danielrey.cimafranca?__tn__=R",
    "text": "Any system we come up with will have its flaws.  To err is human after all and we are living in the kingdom of man, not in the perfect kingdom of God.  Ganun talaga sa separation of church and state, it becomes a legal issue.  Let's not forget why such separation is in our Constitution.  My personal take on it, dont get mad get even kasi nandyan na yan eh.  What can we do legally para bwisitin ang mga Marcos \u00fc",
    "attachments": [],
    "date": "Nov 19, 2016",
    "replyto": "10155103289888912"
  },
  "reply_to": "https://www.facebook.com/stephen.roy.tang/posts/10155102720598912#10155103289888912"
}