{
  "id": "b79ff716-fd5d-4692-a109-947e89b99837",
  "name": "Jvee Veneracion",
  "url": "https://www.facebook.com/jvee.veneracion",
  "text": "A lot of the time frame is rushed. Same question applies to forensics ppl &amp; CSI. There was one news feature on a doctor who diagnosed a patient based on a House ep.",
  "date": "2015-08-27 00:00:04",
  "photo": null,
  "source_url": "https://www.facebook.com/stephen.roy.tang/posts/10154040639008912#10154044498308912",
  "source_obj": {
    "id": "10154044498308912",
    "poster": "Jvee Veneracion",
    "poster_url": "/jvee.veneracion?refid=52&_ft_=mf_story_key.10154040639008912%3Atop_level_post_id.10154040639008912%3Atl_objid.10154040639008912%3Acontent_owner_id_new.632418911%3Athrowback_story_fbid.10154040639008912%3Astory_location.4%3Athid.632418911&__tn__=R",
    "text": "A lot of the time frame is rushed. Same question applies to forensics ppl & CSI. There was one news feature on a doctor who diagnosed a patient based on a House ep.",
    "attachments": [],
    "date": "Aug 27, 2015"
  }
}