{
  "id": "1ff84b5f-bbbe-47b2-9608-2b7b8885b138",
  "name": "Clifton James Sawit",
  "url": "https://www.facebook.com/multipleegos",
  "text": "The &#x27;carry&#x27; situation you describe tends to occur when you party up with friends, who are more likely to have disparate skill levels than quick match teams",
  "date": "2017-01-11 00:01:42",
  "photo": null,
  "source_url": "https://www.facebook.com/stephen.roy.tang/posts/10155266619368912#10155266629683912",
  "source_obj": {
    "id": "10155266629683912",
    "poster": "Clifton James Sawit",
    "poster_url": "/multipleegos?__tn__=R",
    "text": "The 'carry' situation you describe tends to occur when you party up with friends, who are more likely to have disparate skill levels than quick match teams",
    "attachments": [],
    "date": "Jan 11, 2017",
    "replyto": "10155266623438912"
  },
  "reply_to": "https://www.facebook.com/stephen.roy.tang/posts/10155266619368912#10155266623438912"
}