{
  "id": "0878e0b2-ac44-4d22-9d89-13781ac79f5d",
  "name": "Maan Dela Cruz Sicam",
  "url": "https://www.facebook.com/maan.sicam",
  "text": "Roy , pwede. Although, other than Iron Fist, nagustuhan ko naman lahat ...",
  "date": "2018-01-25 00:01:42",
  "photo": null,
  "source_url": "https://www.facebook.com/stephen.roy.tang/posts/10156363653853912#10156365309178912",
  "source_obj": {
    "id": "10156365309178912",
    "poster": "Maan Dela Cruz Sicam",
    "poster_url": "/maan.sicam?__tn__=R",
    "text": "Roy , pwede. Although, other than Iron Fist, nagustuhan ko naman lahat ...",
    "attachments": [],
    "date": "Jan 25, 2018",
    "replyto": "10156364039463912"
  },
  "reply_to": "https://www.facebook.com/stephen.roy.tang/posts/10156363653853912#10156364039463912"
}