{
  "id": "aa855bc5-7784-420a-8f7d-7ff2db9ef4a3",
  "name": "Jvee Veneracion",
  "url": "https://www.facebook.com/jvee.veneracion",
  "text": "Don&#x27;t forget Isle of Dogs. End of the month i think.",
  "date": "2018-05-06 00:00:00",
  "photo": null,
  "source_url": "https://www.facebook.com/stephen.roy.tang/posts/10156618819058912#10156618823588912",
  "source_obj": {
    "id": "10156618823588912",
    "poster": "Jvee Veneracion",
    "poster_url": "/jvee.veneracion?refid=52&_ft_=mf_story_key.10156618819058912%3Atop_level_post_id.10156618819058912%3Atl_objid.10156618819058912%3Acontent_owner_id_new.632418911%3Athrowback_story_fbid.10156618819058912%3Astory_location.4%3Athid.632418911&__tn__=R",
    "text": "Don't forget Isle of Dogs. End of the month i think.",
    "attachments": [],
    "date": "May 6, 2018"
  }
}