{
  "id": "6be48033-5b2f-4944-a197-6316ec92361c",
  "name": "Marco Sancho",
  "url": "https://www.facebook.com/marco.sancho",
  "text": "There&#x27;s only one thing to do with it. Use it. Lol",
  "date": "2016-07-20 00:01:42",
  "photo": null,
  "source_url": "https://www.facebook.com/stephen.roy.tang/posts/10154759411248912#10154759530778912",
  "source_obj": {
    "id": "10154759530778912",
    "poster": "Marco Sancho",
    "poster_url": "/marco.sancho?__tn__=R",
    "text": "There's only one thing to do with it. Use it. Lol",
    "attachments": [],
    "date": "Jul 20, 2016",
    "replyto": "10154759458923912"
  },
  "reply_to": "https://www.facebook.com/stephen.roy.tang/posts/10154759411248912#10154759458923912"
}