{
  "id": "a9843b23-4e84-4fbd-80dc-6696f4950dac",
  "name": "Jaime L. Garcia",
  "url": "https://www.facebook.com/jaime.l.garcia.779",
  "text": "Storage. We tried to hock it, but  it's not saleable online (especially something that can be bought elsewhere). Might just end up saving for a party.",
  "date": "2016-07-01 08:12:35 +0000",
  "photo": null,
  "source_url": "https://www.facebook.com/stephen.roy.tang/posts/10154713441653912:0#10154713759398912",
  "source": "facebook",
  "spam": false,
  "reply_to": "https://www.facebook.com/stephen.roy.tang/posts/10154713441653912:0#10154713702868912"
}