{
  "id": "8f697f89-10e4-4886-badc-3bc1b242b36f",
  "name": "David Ramirez",
  "url": "https://www.facebook.com/profile.php?id=827533990",
  "text": "I imagine there are some stores here that might let you preorder.    The price difference isn't surprising--the  Kinect hardware is probably really pricey. The used games/sharing issue is something that doesn't cost them to avoid, just leaving it up to the publishers. Not forcing 24 hour check-ins is also not complicated.    But yes, it says something that the X-Box team messed up so badly that *the lack* of something on the Playstation counts as desirable features  =P",
  "date": "2013-06-11 20:23:01 +0800",
  "photo": "",
  "source_url": "https://www.facebook.com/stephen.roy.tang/posts/10152280828908912#10152280855478912",
  "source": "facebook",
  "spam": false,
  "reply_to": "https://www.facebook.com/stephen.roy.tang/posts/10152280828908912"
}