{
  "id": "abbc9391-5f55-4126-8d1c-a7045e3a2194",
  "name": "Rico Estrella",
  "url": "https://www.facebook.com/ricoestrella",
  "text": "lol may bukas pa palang video city?",
  "date": "2014-02-05 00:00:00",
  "photo": null,
  "source_url": "https://www.facebook.com/stephen.roy.tang/posts/10152769223278912#10152769233453912",
  "source_obj": {
    "id": "10152769233453912",
    "poster": "Rico Estrella",
    "poster_url": "/ricoestrella?refid=52&_ft_=mf_story_key.10152769223278912%3Atop_level_post_id.10152769223278912%3Atl_objid.10152769223278912%3Acontent_owner_id_new.632418911%3Athrowback_story_fbid.10152769223278912%3Astory_location.4%3Athid.632418911&__tn__=R",
    "text": "lol may bukas pa palang video city?",
    "attachments": [],
    "date": "Feb 5, 2014"
  }
}