{
  "id": "b7b0c8d2-b932-4f78-a2e1-678b8f15bfec",
  "name": "David Ramirez",
  "url": "https://www.facebook.com/profile.php",
  "text": "Manila Manila would actually be a decent name for an 80s themed nightclub  =P",
  "date": "2014-08-29 00:00:01",
  "photo": null,
  "source_url": "https://www.facebook.com/stephen.roy.tang/posts/10153186937488912#10153187175008912",
  "source_obj": {
    "id": "10153187175008912",
    "poster": "David Ramirez",
    "poster_url": "/profile.php?id=827533990&refid=52&_ft_=mf_story_key.10153186937488912%3Atop_level_post_id.10153186937488912%3Atl_objid.10153186937488912%3Acontent_owner_id_new.632418911%3Athrowback_story_fbid.10153186937488912%3Astory_location.4%3Athid.632418911&__tn__=R",
    "text": "Manila Manila would actually be a decent name for an 80s themed nightclub  =P",
    "attachments": [],
    "date": "Aug 29, 2014"
  }
}