{
  "id": "7eb98f09-a59e-4754-bc28-896dbd93aad7",
  "name": "Roy Tang",
  "url": "https://twitter.com/roytang",
  "text": "[@switchfollows](https://twitter.com/switchfollows/) does the format matter? :p Well for you it might haha. I'm joining regardless, with a modified event deck if necessary :D",
  "date": "2011-12-07 15:58:11",
  "photo": "https://pbs.twimg.com/profile_images/1269775872740872192/88S_sBIM_normal.jpg",
  "source_url": "https://twitter.com/roytang/status/144445608948801539/",
  "reply_to": "https://twitter.com/switchfollows/status/144445436441268225/",
  "source": "twitter"
}