{
  "id": "8249a3a1-b3be-4ba5-bdf5-3f46c43e7a73",
  "name": "Roy Tang",
  "url": "https://twitter.com/roytang",
  "text": "[@switchfollows](https://twitter.com/switchfollows/) yeah I think I mostly read the issues from around late 70s to early 80s from you. 92 was written by Scott Lobdell, I'm not sure what Peter David's last issue was. I remember the series quality declining after this particular issue, though I did follow it until it ended",
  "date": "2019-01-12 04:35:00",
  "photo": "https://pbs.twimg.com/profile_images/1269775872740872192/88S_sBIM_normal.jpg",
  "source_url": "https://twitter.com/roytang/status/1083945417631584261/",
  "reply_to": "https://twitter.com/switchfollows/status/1083584269576896512/",
  "source": "twitter"
}