{
  "photo": null,
  "source_url": "https://www.instagram.com/p/CFrKepfhZ4r/#liked-by-488862446",
  "id": "284bdbdc-21bf-4f4b-8746-ddcceb1c220e",
  "source_obj": {
    "author": {
      "photo": "https://webmention.io/avatar/scontent-iad3-1.cdninstagram.com/21946e232b2e4e3c044cd90f3d06647ca4b75def8dcaca4470f9acf02ac22df7.jpg",
      "name": "Clifton Sawit",
      "url": "https://www.instagram.com/multipleegos/",
      "type": "card"
    },
    "published": null,
    "wm-received": "2020-09-29T14:50:59Z",
    "wm-property": "like-of",
    "wm-private": false,
    "wm-id": 860341,
    "like-of": "https://roytang.net/2020/09/nintendo-switch/",
    "type": "entry",
    "wm-source": "https://brid-gy.appspot.com/like/instagram/roytang0400/2408064512361340459_927543231/488862446",
    "url": "https://www.instagram.com/p/CFrKepfhZ4r/#liked-by-488862446",
    "wm-target": "https://roytang.net/2020/09/nintendo-switch/"
  },
  "name": "Clifton Sawit",
  "date": "2020-09-29 14:50:59",
  "url": "https://www.instagram.com/multipleegos/",
  "text": "[Clifton Sawit](https://www.instagram.com/multipleegos/) [liked this](https://www.instagram.com/p/CFrKepfhZ4r/#liked-by-488862446)"
}