{
  "id": "2d8edcd8-fcb4-4ee3-a75f-c2325b1b7b26",
  "name": "Roy Tang",
  "url": "https://www.facebook.com/stephen.roy.tang",
  "text": "David Ramirez  it actually did happen. He retired because he was suspected of being punch drunk. But the series still goes on lol",
  "date": "2018-08-27 00:00:01",
  "photo": null,
  "source_url": "https://www.facebook.com/stephen.roy.tang/posts/10153184237883912#10156874409073912",
  "source_obj": {
    "id": "10156874409073912",
    "poster": "Roy Tang",
    "poster_url": "/stephen.roy.tang?refid=52&_ft_=mf_story_key.10153184237883912%3Atop_level_post_id.10153184237883912%3Atl_objid.10153184237883912%3Acontent_owner_id_new.632418911%3Athrowback_story_fbid.10153184237883912%3Astory_location.4%3Athid.632418911&__tn__=R",
    "text": "David Ramirez  it actually did happen. He retired because he was suspected of being punch drunk. But the series still goes on lol",
    "attachments": [],
    "date": "Aug 27, 2018"
  }
}