{
  "id": "aa3f3b99-675b-41db-ae3f-33c59599568e",
  "name": "Michael Daniel V. Samson",
  "url": "https://www.facebook.com/mdvsamson",
  "text": "Do what I do: use pasta sauce. I prefer Prego, but del Monte four cheese is still a favorite",
  "date": "2013-09-11 00:00:00",
  "photo": null,
  "source_url": "https://www.facebook.com/stephen.roy.tang/posts/10152460300053912#10152460306673912",
  "source_obj": {
    "id": "10152460306673912",
    "poster": "Michael Daniel V. Samson",
    "poster_url": "/mdvsamson?refid=52&_ft_=mf_story_key.10152460300053912%3Atop_level_post_id.10152460300053912%3Atl_objid.10152460300053912%3Acontent_owner_id_new.632418911%3Athrowback_story_fbid.10152460300053912%3Astory_location.4%3Athid.632418911&__tn__=R",
    "text": "Do what I do: use pasta sauce. I prefer Prego, but del Monte four cheese is still a favorite",
    "attachments": [],
    "date": "Sep 11, 2013"
  }
}