{
  "id": "147f0b3b-6824-475e-8189-03e7b0e4a1a7",
  "name": "visa is almost done \u270d\ud83c\udffe\ud83d\udcd6",
  "url": "https://twitter.com/visakanv",
  "text": "[@roytang](https://twitter.com/roytang/) ... i think i broke it, i'm getting \"Gateway Timeout: The gateway did not receive a timely response from the upstream server or application.\"",
  "date": "2019-01-21 16:42:10",
  "photo": "https://pbs.twimg.com/profile_images/1310780119590424576/yPprRCqP_normal.jpg",
  "source_url": "https://twitter.com/visakanv/status/1087389904592502784/",
  "reply_to": "https://twitter.com/visakanv/status/1087348203630997504/"
}