{
  "id": "8c682f09-b9f2-4e3f-8fc2-6cc5bce600dc",
  "name": "Roy Tang",
  "url": "https://www.facebook.com/stephen.roy.tang",
  "text": "<p>Surprise game of Cards Against Humanity (<a href=\"https://twitter.com/CAH/\">@CAH</a>) during lunch</p>\n<p><a href=\"https://www.facebook.com/100000039030121\">Lizbeth Jane Garcia</a> itag daw kita</p>",
  "date": "2015-04-17 13:35:18 +0800",
  "photo": "",
  "source_url": "https://www.facebook.com/stephen.roy.tang/posts/10153711150003912:0",
  "source": "script",
  "spam": false
}