{
  "id": "e6fcff77-8696-40bb-8c85-3e430acfcfbc",
  "name": "Mylee Ejercito",
  "url": "https://www.facebook.com/romancoat",
  "text": "MarisBarney , i hope that what you&#x27;re thinking is true na this allowed us to remember. I worry kasi na the people who are remembering are the &quot;elite&quot; -- we need to make sure we reach out to the rest of the voters and combat the very rampant misinformation out there.",
  "date": "2016-11-23 00:11:45",
  "photo": null,
  "source_url": "https://www.facebook.com/stephen.roy.tang/posts/10155111964538912#10155114836258912",
  "source_obj": {
    "id": "10155114836258912",
    "poster": "Mylee Ejercito",
    "poster_url": "/romancoat?__tn__=R",
    "text": "MarisBarney , i hope that what you're thinking is true na this allowed us to remember. I worry kasi na the people who are remembering are the \"elite\" -- we need to make sure we reach out to the rest of the voters and combat the very rampant misinformation out there.",
    "attachments": [],
    "date": "Nov 23, 2016",
    "replyto": "10155112143918912"
  },
  "reply_to": "https://www.facebook.com/stephen.roy.tang/posts/10155111964538912#10155114824193912"
}