{
  "id": "f45db5bd-b988-4e5d-9b02-adfb20924b01",
  "name": "dominik",
  "url": "https://nona.social/@dominik",
  "text": "<p><span class=\"h-card\" translate=\"no\"><a href=\"https://indieweb.social/@roytang\" class=\"u-url mention\" rel=\"nofollow noopener\" target=\"_blank\">@<span>roytang</span></a></span> my passport says something else than this test \ud83d\ude05</p>",
  "date": "2026-04-18 16:49:39 +0800",
  "photo": "https://cdn.masto.host/indiewebsocial/cache/accounts/avatars/109/378/007/395/325/111/original/0413afd72b9feca0.jpg",
  "source_url": "https://nona.social/users/dominik/statuses/116424846860523367",
  "source": "mastodon",
  "spam": false
}