{
  "id": "faf0a3de-ef33-44ef-84ca-543dff322580",
  "name": "Liza Budlong",
  "url": "https://www.facebook.com/liza.budlong.5",
  "text": "because mayo is more expensive",
  "date": "2017-02-28 00:00:04",
  "photo": null,
  "source_url": "https://www.facebook.com/stephen.roy.tang/posts/10155402985343912#10155403136278912",
  "source_obj": {
    "id": "10155403136278912",
    "poster": "Liza Budlong",
    "poster_url": "/liza.budlong.5?refid=52&_ft_=mf_story_key.10155402985343912%3Atop_level_post_id.10155402985343912%3Atl_objid.10155402985343912%3Acontent_owner_id_new.632418911%3Athrowback_story_fbid.10155402985343912%3Astory_location.4%3Athid.632418911&__tn__=R",
    "text": "because mayo is more expensive",
    "attachments": [],
    "date": "Feb 28, 2017",
    "replies": [
      {
        "id": "10155403162008912",
        "poster": "Jose Zapatos",
        "poster_url": "/jose.zapatos.9?__tn__=R",
        "text": "Better Google \"how to make mayo\" & \"how to make ketchup\".    Mayo is whipped egg whites and ketchup is crushed tomatoes without the skin and seeds?",
        "attachments": [],
        "date": "Feb 28, 2017",
        "replyto": "10155403136278912"
      }
    ]
  }
}