{
  "id": "344963b4-0f33-4a21-adfe-0218c4f833d7",
  "name": "Adrian Cochrane",
  "url": "https://floss.social/@alcinnz",
  "text": "[Adrian Cochrane](https://floss.social/@alcinnz) [shared this](https://mastodon.technology/@roytang/107307779510523971#reblogged-by-77011)",
  "date": "2021-11-20 06:16:14",
  "photo": "https://webmention.io/avatar/cdn.mastodon.technology/944aa923653f5cd8d1df482732e817c7edbc94569b80ad54455b86b4fd9ff4fd.png",
  "source_url": "https://mastodon.technology/@roytang/107307779510523971#reblogged-by-77011",
  "source_obj": {
    "type": "entry",
    "author": {
      "type": "card",
      "name": "Adrian Cochrane",
      "photo": "https://webmention.io/avatar/cdn.mastodon.technology/944aa923653f5cd8d1df482732e817c7edbc94569b80ad54455b86b4fd9ff4fd.png",
      "url": "https://floss.social/@alcinnz"
    },
    "url": "https://mastodon.technology/@roytang/107307779510523971#reblogged-by-77011",
    "published": null,
    "wm-received": "2021-11-20T06:16:14Z",
    "wm-id": 1307661,
    "wm-source": "https://brid.gy/repost/mastodon/@roytang@mastodon.technology/107307779510523971/77011",
    "wm-target": "https://roytang.net/2021/11/couple-word-games/",
    "repost-of": "https://roytang.net/2021/11/couple-word-games/",
    "wm-property": "repost-of",
    "wm-private": false
  }
}