{
  "id": "e437ab88-cfd6-4f4f-82f2-961365a0597a",
  "name": "Roy Tang",
  "url": "https://www.facebook.com/stephen.roy.tang",
  "text": "Yeap",
  "date": "2014-07-04 00:00:03",
  "photo": null,
  "source_url": "https://www.facebook.com/stephen.roy.tang/posts/10153067966258912#10153067982053912",
  "source_obj": {
    "id": "10153067982053912",
    "poster": "Roy Tang",
    "poster_url": "/stephen.roy.tang?refid=52&_ft_=mf_story_key.10153067966258912%3Atop_level_post_id.10153067966258912%3Atl_objid.10153067966258912%3Acontent_owner_id_new.632418911%3Athrowback_story_fbid.10153067966258912%3Astory_location.4%3Athid.632418911&__tn__=R",
    "text": "Yeap",
    "attachments": [],
    "date": "Jul 4, 2014"
  }
}