{
  "id": "f08b85b2-4c1a-4dec-ad88-df6f7a4cbeb4",
  "name": "Nick Solana",
  "url": "https://www.facebook.com/nicksolana",
  "text": "hala...",
  "date": "2014-04-05 00:00:00",
  "photo": null,
  "source_url": "https://www.facebook.com/stephen.roy.tang/posts/10152877741728912#10152877751563912",
  "source_obj": {
    "id": "10152877751563912",
    "poster": "Nick Solana",
    "poster_url": "/nicksolana?refid=52&_ft_=mf_story_key.10152877741728912%3Atop_level_post_id.10152877741728912%3Atl_objid.10152877741728912%3Acontent_owner_id_new.632418911%3Athrowback_story_fbid.10152877741728912%3Astory_location.4%3Athid.632418911&__tn__=R",
    "text": "hala...",
    "attachments": [],
    "date": "Apr 5, 2014"
  }
}