{
  "id": "67c0b30e-2274-4a3e-9300-33e036a63d3c",
  "name": "Roy Tang",
  "url": "https://www.facebook.com/stephen.roy.tang",
  "text": "Standard",
  "date": "2017-03-13 00:01:40",
  "photo": null,
  "source_url": "https://www.facebook.com/stephen.roy.tang/posts/10155443648548912#10155443716333912",
  "source_obj": {
    "id": "10155443716333912",
    "poster": "Roy Tang",
    "poster_url": "/stephen.roy.tang?__tn__=R",
    "text": "Standard",
    "attachments": [],
    "date": "Mar 13, 2017",
    "replyto": "10155443715968912"
  },
  "reply_to": "https://www.facebook.com/stephen.roy.tang/posts/10155443648548912#10155443715968912"
}