{
  "id": "f24e55fd-2a78-40c8-b155-7f9b168f7c5c",
  "name": "Great Dilla",
  "url": "https://twitter.com/greatdilla",
  "text": "[@roytang](https://twitter.com/roytang/) still using it now as we speak.. the other i replaced the USB cable from another mouse. wear and tear i guess.",
  "date": "2016-03-28 18:42:38",
  "photo": "https://pbs.twimg.com/profile_images/1855178518/great_normal.jpg",
  "source_url": "https://twitter.com/greatdilla/status/714523107537489920/",
  "reply_to": "https://twitter.com/greatdilla/status/714515219788095488/"
}