{
  "id": "82ca5455-03aa-4f16-b93f-b6f022c9a923",
  "name": "Jaime L. Garcia",
  "url": "https://www.facebook.com/jaime.l.garcia.779",
  "text": "Eh, no problem. It&#x27;s just funny. XD",
  "date": "2017-06-29 00:03:22",
  "photo": null,
  "source_url": "https://www.facebook.com/stephen.roy.tang/posts/10155804204753912#10155804340723912",
  "source_obj": {
    "id": "10155804340723912",
    "poster": "Jaime L. Garcia",
    "poster_url": "/jaime.l.garcia.779?__tn__=R",
    "text": "Eh, no problem. It's just funny. XD",
    "attachments": [],
    "date": "Jun 29, 2017",
    "replyto": "10155804286728912"
  },
  "reply_to": "https://www.facebook.com/stephen.roy.tang/posts/10155804204753912#10155804286728912"
}