{
  "id": "07435098-edac-4757-aa47-38c44230b3f3",
  "name": "Arthur Abon",
  "url": "https://www.facebook.com/arthur.abon",
  "text": "You would need some AI on it. You can't expect people in an emergency to remember a required syntax.",
  "date": "2018-07-02 13:13:04 +0000",
  "photo": "",
  "source_url": "https://www.facebook.com/stephen.roy.tang/posts/10156745118928912#10156745132498912#10156745311558912",
  "source": "facebook",
  "spam": false,
  "reply_to": "https://www.facebook.com/stephen.roy.tang/posts/10156745118928912#10156745132498912"
}