{
  "id": "890b493d-a99d-4e2d-849b-fe676deffae7",
  "name": "scott",
  "url": "https://carfree.city/@scott",
  "text": "<p><span class=\"h-card\" translate=\"no\"><a href=\"https://indieweb.social/@roytang\" class=\"u-url mention\" rel=\"nofollow noopener noreferrer\" target=\"_blank\">@<span>roytang</span></a></span> directions here (but a little confusing. keep scrolling down to \"Got a bluesky account?\") <a href=\"https://fed.brid.gy/\" rel=\"nofollow noopener noreferrer\" translate=\"no\" target=\"_blank\"><span class=\"invisible\">https://</span><span class=\"\">fed.brid.gy/</span><span class=\"invisible\"></span></a></p>",
  "date": "2024-11-07 14:43:31 +0800",
  "photo": "https://cdn.masto.host/indiewebsocial/cache/accounts/avatars/109/383/837/402/048/703/original/54f9026b04ec9b9a.jpg",
  "source_url": "https://carfree.city/users/scott/statuses/113440313263540588",
  "source": "mastodon",
  "spam": false,
  "reply_to": "https://carfree.city/users/scott/statuses/113440310941758708"
}