{
  "id": "15785f58-9da4-4ac1-8c74-696c1f306944",
  "name": "Roy Tang",
  "url": "https://www.facebook.com/stephen.roy.tang",
  "text": "But it doesn&#x27;t RHYME!",
  "date": "2016-11-25 00:01:42",
  "photo": null,
  "source_url": "https://www.facebook.com/stephen.roy.tang/posts/10155119668548912#10155119689558912",
  "source_obj": {
    "id": "10155119689558912",
    "poster": "Roy Tang",
    "poster_url": "/stephen.roy.tang?__tn__=R",
    "text": "But it doesn't RHYME!",
    "attachments": [],
    "date": "Nov 25, 2016",
    "replyto": "10155119685098912"
  },
  "reply_to": "https://www.facebook.com/stephen.roy.tang/posts/10155119668548912#10155119685098912"
}