{
  "id": "a607e85b-a4d1-4c3f-8428-0add5d1eb1ff",
  "name": "Arthur Abon",
  "url": "https://www.facebook.com/arthur.abon",
  "text": "Also  Roy , the new Zenbooks look good and have decent computing power.",
  "date": "2017-03-29 00:03:20",
  "photo": null,
  "source_url": "https://www.facebook.com/stephen.roy.tang/posts/10155485340128912#10155485373578912",
  "source_obj": {
    "id": "10155485373578912",
    "poster": "Arthur Abon",
    "poster_url": "/arthur.abon?__tn__=R",
    "text": "Also  Roy , the new Zenbooks look good and have decent computing power.",
    "attachments": [],
    "date": "Mar 29, 2017",
    "replyto": "10155485372098912"
  },
  "reply_to": "https://www.facebook.com/stephen.roy.tang/posts/10155485340128912#10155485372098912"
}