{
  "id": "d7240c2f-3c92-470b-a8bd-66a7b3132848",
  "name": "Jonathan Ryan Ang",
  "url": "https://www.facebook.com/jonathanryan.ang",
  "text": "you need more pro binay friends",
  "date": "2015-12-10 00:05:01",
  "photo": null,
  "source_url": "https://www.facebook.com/stephen.roy.tang/posts/10154239469608912#10154239510483912",
  "source_obj": {
    "id": "10154239510483912",
    "poster": "Jonathan Ryan Ang",
    "poster_url": "/jonathanryan.ang?__tn__=R",
    "text": "you need more pro binay friends",
    "attachments": [],
    "date": "Dec 10, 2015",
    "replyto": "10154239488683912"
  },
  "reply_to": "https://www.facebook.com/stephen.roy.tang/posts/10154239469608912#10154239488683912"
}