{
  "id": "d741e1db-d269-4f88-b1fd-d9652a013c65",
  "name": "Roy Tang",
  "url": "https://www.facebook.com/stephen.roy.tang",
  "text": "We&#x27;ll never know!",
  "date": "2016-12-24 00:01:40",
  "photo": null,
  "source_url": "https://www.facebook.com/stephen.roy.tang/posts/10155212566278912#10155212602538912",
  "source_obj": {
    "id": "10155212602538912",
    "poster": "Roy Tang",
    "poster_url": "/stephen.roy.tang?__tn__=R",
    "text": "We'll never know!",
    "attachments": [],
    "date": "Dec 24, 2016",
    "replyto": "10155212601728912"
  },
  "reply_to": "https://www.facebook.com/stephen.roy.tang/posts/10155212566278912#10155212601728912"
}