{
  "id": "047c13cd-560b-41ae-baca-0fbab281db1f",
  "name": "Roy Tang",
  "url": "https://www.facebook.com/stephen.roy.tang",
  "text": "@Maan: Too late, binayaran ko na  :p    Also, it&#x27;s not like I was late for a day or so; I just realized when I got this month&#x27;s payment that I didn&#x27;t pay last month&#x27;s bill. (I actually thought I did but it turns out I didn&#x27;t O_o). ",
  "date": "2010-03-09 00:00:02",
  "photo": null,
  "source_url": "https://www.facebook.com/stephen.roy.tang/posts/352660162621#10150855220907622"
}