{
  "id": "35573c74-fe8d-443b-983a-afa7586f9d32",
  "name": "Ramon Alcasabas",
  "url": "https://facebook.com/ramon.alcasabas",
  "text": "and the SPA only authorizes his lawyer (not the public) to receive the certification requested in the carefully worded SPA, which the latter may or may not disclose - on time. its not a waiver to the public to see his accounts",
  "date": "2016-05-04 13:50:00",
  "photo": "",
  "source_url": "https://www.facebook.com/stephen.roy.tang/posts/10154576323798912#10154576846153912",
  "source": "facebook"
}