{
  "id": "05e3ad29-f20d-414a-b6a8-dc206ec20093",
  "name": "hungryroy",
  "url": "https://www.reddit.com/u/hungryroy",
  "text": "Looks like it's this one: http://skyrim.nexusmods.com/mods/12452/? (must have been renamed for some reason), but I can't use it as it requires Dawnguard which I don't have (waiting for Steam sale to get it)\n\nOh well, guess I'll just wait.",
  "date": "2013-06-02 11:03:49 +0800",
  "photo": null,
  "source_url": "https://www.reddit.com/r/skyrim/comments/1fi0a2/are_there_are_any_mods_that_add_a_chance_of/caaiscc/",
  "source": "reddit",
  "spam": false,
  "reply_to": "https://www.reddit.com/r/skyrim/comments/1fi0a2/are_there_are_any_mods_that_add_a_chance_of/caagach/"
}